diffsyncer-1.1.1.dist-info/METADATA
diffsyncer-1.1.1.dist-info/WHEEL
diffsyncer-1.1.1.dist-info/entry_points.txt
diffsyncer-1.1.1.dist-info/licenses/LICENSE
diffsyncer/.DS_Store
diffsyncer/.gitignore
diffsyncer/__init__.py
diffsyncer/__main__.py
diffsyncer/apis.py
diffsyncer/auth.py
diffsyncer/cli.py
diffsyncer/config.py
diffsyncer/decoder.py
diffsyncer/encoder.py
diffsyncer/git.py
diffsyncer/logger.py
diffsyncer/server.py
diffsyncer/static/assets/Index-DWR2Zx2l.css
diffsyncer/static/assets/Index-Do9NOwrC.js
diffsyncer/static/assets/elementplus-B-iJGUzg.js
diffsyncer/static/assets/index-Bp83w_qS.css
diffsyncer/static/assets/logo-CPmPqqKk.png
diffsyncer/static/assets/vue-CFoKlS7q.js
diffsyncer/static/assets/wasm-CEaAGFph.js
diffsyncer/static/favicon.ico
diffsyncer/static/index.html
diffsyncer/static/index.js
diffsyncer/syncer.py
diffsyncer/utils.py
diffsyncer-1.1.1.dist-info/RECORD
