Metadata-Version: 2.1
Name: diffsyncer
Version: 1.1.1
Summary: A tool to auto sync git diffs to a remote server
Keywords: diffsyncer,git-diff,syncer
Home-page: https://github.com/yugasun/diffsyncer
Author-Email: Yuga Sun <yuga.sun.bj@gmail.com>
Maintainer-Email: Yuga Sun <yuga.sun.bj@gmail.com>
License:                                  Apache License
Classifier: Programming Language :: Python :: 3
Classifier: License :: OSI Approved :: Apache Software License
Classifier: Operating System :: OS Independent
Project-URL: Homepage, https://github.com/yugasun/diffsyncer
Project-URL: Issues, https://github.com/yugasun/diffsyncer/issues
Project-URL: Documentation, https://github.com/yugasun/diffsyncer
Project-URL: Repository, https://github.com/yugasun/diffsyncer
Requires-Python: >=3.10
Requires-Dist: qrcode==7.4.2
Requires-Dist: cryptography==42.0.8
Requires-Dist: zstd==1.5.5.1
Requires-Dist: lz4==4.3.3
Requires-Dist: zxing==1.0.3
Requires-Dist: pyzbar==0.1.9
Requires-Dist: pillow==10.4.0
Requires-Dist: fastapi==0.111.0
Requires-Dist: uvicorn==0.30.0
Requires-Dist: GitPython==3.1.43
Requires-Dist: pydotenv==0.0.7
Requires-Dist: jinja2==3.1.4; platform_system != "Windows"
Requires-Dist: click==8.1.7
Requires-Dist: pyjwt==2.8.0
Requires-Dist: bcrypt==4.0.1
Requires-Dist: passlib==1.7.4
